[
    {
        "site": "simplyHired",
        "lastScraped": "2020-12-19T09:04:58.603Z",
        "entries": 167,
        "position": 167,
        "company": 167,
        "contact": 20,
        "location": 167,
        "posted": 167,
        "due": 4,
        "start": 6,
        "end": 0,
        "compensation": 46,
        "qualifications": 52,
        "skills": 167,
        "description": 167,
        "remote": 28
    },
    {
        "site": "LinkedIn",
        "lastScraped": "2020-12-16T21:20:46.880Z",
        "entries": 90,
        "position": 90,
        "company": 90,
        "contact": 10,
        "location": 90,
        "posted": 90,
        "due": 4,
        "start": 5,
        "end": 0,
        "compensation": 15,
        "qualifications": 32,
        "skills": 90,
        "description": 90,
        "remote": 15
    },
    {
        "site": "ZipRecruiter",
        "lastScraped": "2020-12-19T09:09:54.479Z",
        "entries": 93,
        "position": 93,
        "company": 93,
        "contact": 9,
        "location": 93,
        "posted": 92,
        "due": 3,
        "start": 4,
        "end": 0,
        "compensation": 15,
        "qualifications": 42,
        "skills": 93,
        "description": 93,
        "remote": 21
    },
    {
        "site": "Monster",
        "lastScraped": "2020-12-19T09:04:11.629Z",
        "entries": 9,
        "position": 9,
        "company": 9,
        "contact": 2,
        "location": 9,
        "posted": 9,
        "due": 0,
        "start": 0,
        "end": 0,
        "compensation": 1,
        "qualifications": 5,
        "skills": 9,
        "description": 9,
        "remote": 0
    },
    {
        "site": "YouTern",
        "lastScraped": "2020-12-19T09:08:15.932Z",
        "entries": 1,
        "position": 1,
        "company": 1,
        "contact": 0,
        "location": 1,
        "posted": 1,
        "due": 1,
        "start": 0,
        "end": 0,
        "compensation": 1,
        "qualifications": 1,
        "skills": 1,
        "description": 1,
        "remote": 0
    },
    {
        "site": "iHireTech",
        "lastScraped": "2020-12-19T08:37:50.377Z",
        "entries": 150,
        "position": 150,
        "company": 150,
        "contact": 16,
        "location": 150,
        "posted": 150,
        "due": 2,
        "start": 12,
        "end": 0,
        "compensation": 22,
        "qualifications": 59,
        "skills": 150,
        "description": 150,
        "remote": 17
    },
    {
        "site": "Glassdoor",
        "lastScraped": "2020-12-19T08:31:32.869Z",
        "entries": 60,
        "position": 60,
        "company": 60,
        "contact": 6,
        "location": 60,
        "posted": 60,
        "due": 2,
        "start": 4,
        "end": 0,
        "compensation": 13,
        "qualifications": 25,
        "skills": 60,
        "description": 60,
        "remote": 11
    },
    {
        "site": "Indeed",
        "lastScraped": "2020-12-19T08:42:15.386Z",
        "entries": 298,
        "position": 298,
        "company": 298,
        "contact": 31,
        "location": 298,
        "posted": 297,
        "due": 6,
        "start": 13,
        "end": 0,
        "compensation": 72,
        "qualifications": 100,
        "skills": 298,
        "description": 298,
        "remote": 57
    },
    {
        "site": "Idealist",
        "lastScraped": "2020-10-02T02:35:29.833Z",
        "entries": 4,
        "position": 4,
        "company": 4,
        "contact": 0,
        "location": 4,
        "posted": 4,
        "due": 1,
        "start": 1,
        "end": 0,
        "compensation": 2,
        "qualifications": 1,
        "skills": 3,
        "description": 4,
        "remote": 2
    },
    {
        "site": "AngelList",
        "lastScraped": "2020-10-02T02:39:38.626Z",
        "entries": 549,
        "position": 549,
        "company": 549,
        "contact": 19,
        "location": 549,
        "posted": 0,
        "due": 3,
        "start": 5,
        "end": 0,
        "compensation": 127,
        "qualifications": 31,
        "skills": 516,
        "description": 549,
        "remote": 414
    },
    {
        "site": "Stackoverflow",
        "lastScraped": "2020-12-19T09:06:35.361Z",
        "entries": 7,
        "position": 7,
        "company": 7,
        "contact": 0,
        "location": 7,
        "posted": 7,
        "due": 1,
        "start": 2,
        "end": 0,
        "compensation": 2,
        "qualifications": 1,
        "skills": 7,
        "description": 7,
        "remote": 1
    },
    {
        "site": "ACM",
        "lastScraped": "2020-12-19T08:20:53.975Z",
        "entries": 157,
        "position": 157,
        "company": 157,
        "contact": 3,
        "location": 157,
        "posted": 0,
        "due": 22,
        "start": 7,
        "end": 0,
        "compensation": 10,
        "qualifications": 49,
        "skills": 157,
        "description": 157,
        "remote": 1
    },
    {
        "site": "Coolworks",
        "lastScraped": "2020-12-07T03:45:08.464Z",
        "entries": 6,
        "position": 6,
        "company": 6,
        "contact": 6,
        "location": 6,
        "posted": 6,
        "due": 1,
        "start": 1,
        "end": 0,
        "compensation": 2,
        "qualifications": 1,
        "skills": 6,
        "description": 6,
        "remote": 0
    },
    {
        "site": "Aexpress",
        "lastScraped": "2020-12-19T08:27:27.184Z",
        "entries": 10,
        "position": 10,
        "company": 10,
        "contact": 10,
        "location": 10,
        "posted": 0,
        "due": 1,
        "start": 0,
        "end": 0,
        "compensation": 0,
        "qualifications": 2,
        "skills": 10,
        "description": 10,
        "remote": 0
    },
    {
        "site": "Apple",
        "lastScraped": "2020-12-16T21:49:42.568Z",
        "entries": 38,
        "position": 38,
        "company": 38,
        "contact": 1,
        "location": 38,
        "posted": 38,
        "due": 0,
        "start": 0,
        "end": 0,
        "compensation": 0,
        "qualifications": 0,
        "skills": 33,
        "description": 38,
        "remote": 0
    },
    {
        "site": "Manual",
        "lastScraped": "",
        "entries": 1,
        "position": 1,
        "company": 1,
        "contact": 0,
        "location": 1,
        "posted": 0,
        "due": 1,
        "start": 1,
        "end": 0,
        "compensation": 1,
        "qualifications": 0,
        "skills": 1,
        "description": 1,
        "remote": 0
    },
    {
        "site": "Total",
        "lastScraped": "2020-12-19T09:09:54.479Z",
        "entries": 1640,
        "position": 1640,
        "company": 1640,
        "contact": 133,
        "location": 1640,
        "posted": 921,
        "due": 52,
        "start": 61,
        "end": 0,
        "compensation": 329,
        "qualifications": 401,
        "skills": 1601,
        "description": 1640,
        "remote": 567
    }
]